countrystatecity_countries
