Metadata-Version: 2.4
Name: countrystatecity-countries
Version: 1.0.0
Summary: Type-safe Python package for countries, states, and cities data with 250+ countries, 5000+ states, and 151K+ cities. Features Pydantic models, lazy loading, and comprehensive geographic metadata.
Author-email: dr5hn <support@countrystatecity.in>
Maintainer-email: dr5hn <support@countrystatecity.in>
License: Open Database License (ODbL) v1.0
Project-URL: Homepage, https://github.com/dr5hn/countrystatecity-pypi
Project-URL: Documentation, https://github.com/dr5hn/countrystatecity-pypi/tree/master/python/packages/countries
Project-URL: Repository, https://github.com/dr5hn/countrystatecity-pypi
Project-URL: Source, https://github.com/dr5hn/countrystatecity-pypi/tree/master/python/packages/countries
Project-URL: Issues, https://github.com/dr5hn/countrystatecity-pypi/issues
Project-URL: Changelog, https://github.com/dr5hn/countrystatecity-pypi/blob/master/python/packages/countries/CHANGELOG.md
Keywords: countries,states,cities,geography,geolocation,timezone,translations,iso,lazy-loading,type-hints,pydantic
Classifier: Development Status :: 5 - Production/Stable
Classifier: Intended Audience :: Developers
Classifier: Programming Language :: Python :: 3
Classifier: Programming Language :: Python :: 3.8
Classifier: Programming Language :: Python :: 3.9
Classifier: Programming Language :: Python :: 3.10
Classifier: Programming Language :: Python :: 3.11
Classifier: Programming Language :: Python :: 3.12
Classifier: Topic :: Software Development :: Libraries :: Python Modules
Classifier: Typing :: Typed
Requires-Python: >=3.8
License-File: LICENSE
Requires-Dist: pydantic<3.0.0,>=2.0.0
Provides-Extra: dev
Requires-Dist: pytest>=7.0.0; extra == "dev"
Requires-Dist: pytest-cov>=4.0.0; extra == "dev"
Requires-Dist: mypy>=1.0.0; extra == "dev"
Requires-Dist: black>=23.0.0; extra == "dev"
Requires-Dist: isort>=5.0.0; extra == "dev"
Requires-Dist: ruff>=0.1.0; extra == "dev"
Dynamic: license-file
